views_mapper2/.DS_Store
views_mapper2/BBoxWriter.py
views_mapper2/__init__.py
views_mapper2/assets/.DS_Store
views_mapper2/assets/logo_transparent.png
views_mapper2/color.py
views_mapper2/config.py
views_mapper2/dictionary_writer.py
views_mapper2/label_writer.py
views_mapper2/mapper2.py
views_mapper2/utils.py
views_mapper2-1.10.1.dist-info/WHEEL
views_mapper2-1.10.1.dist-info/METADATA
views_mapper2-1.10.1.dist-info/RECORD
