Metadata-Version: 2.1
Name: views-mapper2
Version: 1.10.1
Summary: Mapper version 2 for viewser
Author: Malika
Author-email: malikarakh@gmail.com
Requires-Python: >=3.9
Classifier: Programming Language :: Python :: 3
Classifier: Programming Language :: Python :: 3.10
Classifier: Programming Language :: Python :: 3.9
Requires-Dist: contextily (>=1.2.0)
Requires-Dist: geopandas (>=0.11.0)
Requires-Dist: ingester3 (>=1.4.2)
Requires-Dist: matplotlib (>=3.4.3)
Requires-Dist: numpy (>=1.20.3)
Requires-Dist: pycountry (>=20.7.3)
Requires-Dist: sqlalchemy (>=1.4.29)
